{
  "0001": "Anxhu",
  "0002": "CactusJab",
  "0003": "formularun",
  "0004": "BitSimon",
  "0005": "BitSimon",
  "0006": "BitSimon",
  "0007": "CactusJab",
  "0008": "CactusJab",
  "0009": "JamBone",
  "0010": "Captain Loki",
  "0011": "Ricky Vaughn",
  "0012": "farsider350",
  "0013": "electrogiraffe",
  "0014": "BitSimon",
  "0015": "Captain Loki",
  "0016": "farsider350",
  "0017": "Captain Loki",
  "0018": "formularun",
  "0019": "Captain Loki",
  "0020": "Anxhu",
  "0021": "Anxhu",
  "0022": "BitSimon",
  "0023": "<anonymous>",
  "0024": "CactusJab",
  "0025": "Anxhu",
  "0026": "Anxhu",
  "0027": "formularun",
  "0028": "Boomshakalaka",
  "0029": "trespasser3",
  "0030": "Ricky Vaughn",
  "0031": "Anxhu",
  "0032": "JamBone",
  "0033": "Boomshakalaka",
  "0034": "Ricky Vaughn",
  "0035": "Boomshakalaka",
  "0036": "Ricky Vaughn",
  "0037": "Ricky Vaughn",
  "0038": "Anxhu",
  "0039": "Captain Loki",
  "0040": "Anxhu",
  "0041": "Captain Loki",
  "0042": "Anxhu",
  "0043": "Captain Loki",
  "0044": "Captain Loki",
  "0045": "Ricky Vaughn",
  "0046": "Ricky Vaughn",
  "0047": "Captain Loki",
  "0048": "xXTrevXx",
  "0049": "Anxhu",
  "0050": "Ricky Vaughn",
  "0051": "CactusJab"
}
